<?xml version="1.0" encoding="UTF-8" ?>
<holidays>
  <holiday>
    <locale>es-ES</locale>
    <region></region>
    <date>2018-01-01</date>
    <description>Año Nuevo</description>
    <type>NF</type>
    <notes></notes>
  </holiday>
  <holiday>
    <locale>es-ES</locale>
    <region></region>
    <date>2018-01-06</date>
    <description>Epifanía del Señor</description>
    <type>NRF</type>
    <notes></notes>
  </holiday>
  <holiday>
    <locale>es-ES</locale>
    <region></region>
    <date>2018-03-30</date>
    <description>Viernes Santo</description>
    <type>NRV</type>
    <notes></notes>
  </holiday>
  <holiday>
    <locale>es-ES</locale>
    <region></region>
    <date>2018-04-01</date>
    <description>Pascua</description>
    <type>NRV</type>
    <notes></notes>
  </holiday>
  <holiday>
    <locale>es-ES</locale>
    <region></region>
    <date>2018-05-01</date>
    <description>Fiesta del Trabajo</description>
    <type>NF</type>
    <notes></notes>
  </holiday>
  <holiday>
    <locale>es-ES</locale>
    <region></region>
    <date>2018-08-15</date>
    <description>Asunción de la Virgen</description>
    <type>NRF</type>
    <notes></notes>
  </holiday>
  <holiday>
    <locale>es-ES</locale>
    <region></region>
    <date>2018-10-12</date>
    <description>Fiesta Nacional de España</description>
    <type>NF</type>
    <notes></notes>
  </holiday>
  <holiday>
    <locale>es-ES</locale>
    <region></region>
    <date>2018-11-01</date>
    <description>Todos los Santos</description>
    <type>NRF</type>
    <notes></notes>
  </holiday>
  <holiday>
    <locale>es-ES</locale>
    <region></region>
    <date>2018-12-06</date>
    <description>Día de la Constitución Española</description>
    <type>NF</type>
    <notes></notes>
  </holiday>
  <holiday>
    <locale>es-ES</locale>
    <region></region>
    <date>2018-12-08</date>
    <description>Inmaculada Concepción</description>
    <type>NRF</type>
    <notes></notes>
  </holiday>
  <holiday>
    <locale>es-ES</locale>
    <region></region>
    <date>2018-12-25</date>
    <description>Navidad</description>
    <type>NRF</type>
    <notes></notes>
  </holiday>
</holidays>
